{"assets":{"assets":{"asset":[{"name":"arabian_bigtb_64_a_0_0","x":"34","y":"42"},{"name":"arabian_bigtb_64_a_2_0","flipH":"1","source":"arabian_bigtb_64_a_0_0","x":"34","y":"42"},{"name":"arabian_bigtb_64_b_0_0","x":"70","y":"24"},{"name":"arabian_bigtb_64_b_2_0","flipH":"1","source":"arabian_bigtb_64_b_0_0","x":"70","y":"24"},{"name":"arabian_bigtb_64_c_0_0","x":"36","y":"8"},{"name":"arabian_bigtb_64_c_2_0","flipH":"1","source":"arabian_bigtb_64_c_0_0","x":"36","y":"8"},{"name":"arabian_bigtb_64_d_0_0","x":"4","y":"-10"},{"name":"arabian_bigtb_64_d_2_0","flipH":"1","source":"arabian_bigtb_64_d_0_0","x":"4","y":"-10"},{"name":"arabian_bigtb_64_sd_0_0","x":"61","y":"-9"},{"name":"arabian_bigtb_64_sd_2_0","x":"93","y":"-9"},{"name":"arabian_bigtb_icon_a","x":"14","y":"9"},{"name":"arabian_bigtb_32_a_0_0","x":"16","y":"20"},{"name":"arabian_bigtb_32_a_2_0","flipH":"1","source":"arabian_bigtb_32_a_0_0","x":"16","y":"20"},{"name":"arabian_bigtb_32_b_0_0","x":"35","y":"11"},{"name":"arabian_bigtb_32_b_2_0","flipH":"1","source":"arabian_bigtb_32_b_0_0","x":"35","y":"11"},{"name":"arabian_bigtb_32_c_0_0","x":"17","y":"3"},{"name":"arabian_bigtb_32_c_2_0","flipH":"1","source":"arabian_bigtb_32_c_0_0","x":"17","y":"3"},{"name":"arabian_bigtb_32_d_0_0","x":"1","y":"-6"},{"name":"arabian_bigtb_32_d_2_0","flipH":"1","source":"arabian_bigtb_32_d_0_0","x":"1","y":"-6"},{"name":"arabian_bigtb_32_sd_0_0","x":"30","y":"-6"},{"name":"arabian_bigtb_32_sd_2_0","x":"46","y":"-6"}]}},"index":{"object":{"type":"arabian_bigtb","visualization":"furniture_static","logic":"furniture_basic"}},"logic":{"objectData":{"type":"arabian_bigtb","model":{"dimensions":{"x":"3","y":"2","z":"1.1"},"directions":{"direction":[{"id":"0"},{"id":"90"}]}}}},"manifest":{"manifest":{"library":{"name":"arabian_bigtb","version":"0.1","assets":{"asset":[{"name":"index","mimeType":"text/xml"},{"name":"arabian_bigtb_visualization","mimeType":"text/xml"},{"name":"arabian_bigtb_assets","mimeType":"text/xml"},{"name":"arabian_bigtb_logic","mimeType":"text/xml"},{"name":"arabian_bigtb_64_a_0_0","mimeType":"image/png"},{"name":"arabian_bigtb_64_b_0_0","mimeType":"image/png"},{"name":"arabian_bigtb_64_c_0_0","mimeType":"image/png"},{"name":"arabian_bigtb_64_d_0_0","mimeType":"image/png"},{"name":"arabian_bigtb_64_sd_0_0","mimeType":"image/png"},{"name":"arabian_bigtb_64_sd_2_0","mimeType":"image/png"},{"name":"arabian_bigtb_icon_a","mimeType":"image/png"},{"name":"arabian_bigtb_32_a_0_0","mimeType":"image/png"},{"name":"arabian_bigtb_32_b_0_0","mimeType":"image/png"},{"name":"arabian_bigtb_32_c_0_0","mimeType":"image/png"},{"name":"arabian_bigtb_32_d_0_0","mimeType":"image/png"},{"name":"arabian_bigtb_32_sd_0_0","mimeType":"image/png"},{"name":"arabian_bigtb_32_sd_2_0","mimeType":"image/png"}]}}}},"visualization":{"visualizationData":{"type":"arabian_bigtb","graphics":{"visualization":[{"size":"32","layerCount":"4","angle":"45","layers":{"layer":[{"id":"1","z":"900"},{"id":"2","z":"1900"},{"id":"3","z":"2900"}]},"directions":{"direction":[{"id":"0"},{"id":"2"}]}},{"size":"64","layerCount":"4","angle":"45","layers":{"layer":[{"id":"1","z":"1000"},{"id":"2","z":"2000"},{"id":"3","z":"3000"}]},"directions":{"direction":[{"id":"0"},{"id":"2"}]}},{"size":"1","layerCount":"1","angle":"360","directions":{"direction":{"id":"0"}}}]}}},"sprites":{"arabian_bigtb_32_a_0_0":{"left":"0","top":"0","width":"35","height":"18"},"arabian_bigtb_32_b_0_0":{"left":"63","top":"0","width":"70","height":"23"},"arabian_bigtb_32_c_0_0":{"left":"133","top":"0","width":"70","height":"23"},"arabian_bigtb_32_d_0_0":{"left":"154","top":"23","width":"37","height":"27"},"arabian_bigtb_32_sd_0_0":{"left":"0","top":"23","width":"77","height":"26"},"arabian_bigtb_32_sd_2_0":{"left":"77","top":"23","width":"77","height":"26"},"arabian_bigtb_64_a_0_0":{"left":"0","top":"50","width":"70","height":"35"},"arabian_bigtb_64_b_0_0":{"left":"70","top":"50","width":"138","height":"44"},"arabian_bigtb_64_c_0_0":{"left":"0","top":"94","width":"140","height":"44"},"arabian_bigtb_64_d_0_0":{"left":"140","top":"94","width":"73","height":"53"},"arabian_bigtb_64_sd_0_0":{"left":"0","top":"147","width":"154","height":"53"},"arabian_bigtb_64_sd_2_0":{"left":"0","top":"200","width":"154","height":"53"},"arabian_bigtb_icon_a":{"left":"35","top":"0","width":"28","height":"19"}}}