{"assets":{"assets":{"asset":[{"name":"classic2_napkin_64_sd_4_0","x":"16","y":"6"},{"name":"classic2_napkin_64_a_4_0","x":"16","y":"22"},{"name":"classic2_napkin_icon_a","x":"14","y":"14"},{"name":"classic2_napkin_64_sd_2_0","flipH":"1","source":"classic2_napkin_64_sd_4_0","x":"16","y":"6"},{"name":"classic2_napkin_64_a_2_0","flipH":"1","source":"classic2_napkin_64_a_4_0","x":"16","y":"22"}]}},"index":{"object":{"type":"classic2_napkin","visualization":"furniture_static","logic":"furniture_basic"}},"logic":{"objectData":{"type":"classic2_napkin","model":{"dimensions":{"x":"1","y":"1","z":"1"},"directions":{"direction":[{"id":"180"},{"id":"90"}]}}}},"manifest":{"manifest":{"library":{"name":"classic2_napkin","version":"0.1","assets":{"asset":[{"name":"index","mimeType":"text/xml"},{"name":"classic2_napkin_visualization","mimeType":"text/xml"},{"name":"classic2_napkin_assets","mimeType":"text/xml"},{"name":"classic2_napkin_logic","mimeType":"text/xml"},{"name":"classic2_napkin_64_sd_4_0","mimeType":"image/png"},{"name":"classic2_napkin_64_a_4_0","mimeType":"image/png"},{"name":"classic2_napkin_icon_a","mimeType":"image/png"}]}}}},"visualization":{"visualizationData":{"type":"classic2_napkin","graphics":{"visualization":[{"size":"1","layerCount":"1","angle":"360"},{"size":"32","layerCount":"1","angle":"45","layers":null,"directions":{"direction":[{"id":"4"},{"id":"2"}]},"colors":null,"animations":null},{"size":"64","layerCount":"1","angle":"45","layers":null,"directions":{"direction":[{"id":"4"},{"id":"2"}]},"colors":null,"animations":null,"postures":null,"gestures":null}]}}},"sprites":{"classic2_napkin_64_a_4_0":{"left":"0","top":"0","width":"31","height":"31"},"classic2_napkin_64_sd_4_0":{"left":"0","top":"31","width":"31","height":"16"},"classic2_napkin_icon_a":{"left":"0","top":"47","width":"29","height":"29"}}}