{"assets":{"assets":{"asset":[{"name":"room_hcl15_tree1_64_sd_0_0","x":"19","y":"8"},{"name":"room_hcl15_tree1_64_a_0_0","x":"20","y":"41"},{"name":"room_hcl15_tree1_64_b_0_0","x":"21","y":"85"},{"name":"room_hcl15_tree1_64_b_0_1","x":"12","y":"104"},{"name":"room_hcl15_tree1_64_b_0_2","x":"7","y":"40"},{"name":"room_hcl15_tree1_icon_a","x":"6","y":"14"},{"name":"room_hcl15_tree1_64_sd_2_0","source":"room_hcl15_tree1_64_sd_0_0","x":"19","y":"8"},{"name":"room_hcl15_tree1_64_a_2_0","source":"room_hcl15_tree1_64_a_0_0","x":"20","y":"41"},{"name":"room_hcl15_tree1_64_b_2_0","flipH":"1","source":"room_hcl15_tree1_64_b_0_0","x":"21","y":"85"},{"name":"room_hcl15_tree1_64_b_2_1","flipH":"1","source":"room_hcl15_tree1_64_b_0_1","x":"12","y":"104"},{"name":"room_hcl15_tree1_64_b_2_2","flipH":"1","source":"room_hcl15_tree1_64_b_0_2","x":"7","y":"40"}]}},"index":{"object":{"type":"room_hcl15_tree1","visualization":"furniture_animated","logic":"furniture_multistate"}},"logic":{"objectData":{"type":"room_hcl15_tree1","model":{"dimensions":{"x":"1","y":"1","z":"1"},"directions":{"direction":[{"id":"0"},{"id":"90"}]}}}},"manifest":{"manifest":{"library":{"name":"room_hcl15_tree1","version":"0.1","assets":{"asset":[{"name":"index","mimeType":"text/xml"},{"name":"room_hcl15_tree1_visualization","mimeType":"text/xml"},{"name":"room_hcl15_tree1_assets","mimeType":"text/xml"},{"name":"room_hcl15_tree1_logic","mimeType":"text/xml"},{"name":"room_hcl15_tree1_64_sd_0_0","mimeType":"image/png"},{"name":"room_hcl15_tree1_64_a_0_0","mimeType":"image/png"},{"name":"room_hcl15_tree1_64_b_0_0","mimeType":"image/png"},{"name":"room_hcl15_tree1_64_b_0_1","mimeType":"image/png"},{"name":"room_hcl15_tree1_64_b_0_2","mimeType":"image/png"},{"name":"room_hcl15_tree1_icon_a","mimeType":"image/png"}]}}}},"visualization":{"visualizationData":{"type":"room_hcl15_tree1","graphics":{"visualization":[{"size":"1","layerCount":"1","angle":"360"},{"size":"32","layerCount":"1","angle":"45","layers":null,"directions":{"direction":[{"id":"0"},{"id":"2"}]},"colors":null,"animations":null},{"size":"64","layerCount":"2","angle":"45","layers":{"layer":{"id":"0"}},"directions":{"direction":[{"id":"0"},{"id":"2"}]},"colors":null,"animations":{"animation":[{"id":"0","animationLayer":[{"id":"0"},{"id":"1"}]},{"id":"1","animationLayer":[{"id":"0"},{"id":"1","frameSequence":{"frame":{"id":"1"}}}]},{"id":"2","animationLayer":[{"id":"0"},{"id":"1","frameSequence":{"frame":{"id":"2"}}}]}]},"postures":null,"gestures":null}]}}},"sprites":{"room_hcl15_tree1_64_a_0_0":{"left":"0","top":"49","width":"40","height":"48"},"room_hcl15_tree1_64_b_0_0":{"left":"0","top":"175","width":"42","height":"52"},"room_hcl15_tree1_64_b_0_1":{"left":"0","top":"97","width":"27","height":"78"},"room_hcl15_tree1_64_b_0_2":{"left":"0","top":"0","width":"14","height":"8"},"room_hcl15_tree1_64_sd_0_0":{"left":"0","top":"30","width":"37","height":"19"},"room_hcl15_tree1_icon_a":{"left":"14","top":"0","width":"14","height":"30"}}}