{"assets":{"assets":{"asset":[{"name":"hblooza_chicken_32_sd_0_0","x":"17","y":"8"},{"name":"hblooza_chicken_32_a_0_0","x":"18","y":"67"},{"name":"hblooza_chicken_32_b_0_0","x":"15","y":"43"},{"name":"hblooza_chicken_32_b_0_1","x":"13","y":"43"},{"name":"hblooza_chicken_32_b_0_2","x":"13","y":"43"},{"name":"hblooza_chicken_32_b_0_3","x":"13","y":"43"},{"name":"hblooza_chicken_64_sd_0_0","x":"33","y":"16"},{"name":"hblooza_chicken_64_a_0_0","x":"34","y":"134"},{"name":"hblooza_chicken_64_b_0_0","x":"29","y":"84"},{"name":"hblooza_chicken_64_b_0_1","x":"24","y":"84"},{"name":"hblooza_chicken_64_b_0_2","x":"24","y":"84"},{"name":"hblooza_chicken_64_b_0_3","x":"25","y":"84"},{"name":"hblooza_chicken_icon_a","x":"12","y":"14"},{"name":"hblooza_chicken_32_sd_2_0","flipH":"1","source":"hblooza_chicken_32_sd_0_0","x":"17","y":"8"},{"name":"hblooza_chicken_32_a_2_0","flipH":"1","source":"hblooza_chicken_32_a_0_0","x":"18","y":"67"},{"name":"hblooza_chicken_32_b_2_0","flipH":"1","source":"hblooza_chicken_32_b_0_0","x":"15","y":"43"},{"name":"hblooza_chicken_32_b_2_1","flipH":"1","source":"hblooza_chicken_32_b_0_1","x":"13","y":"43"},{"name":"hblooza_chicken_32_b_2_2","flipH":"1","source":"hblooza_chicken_32_b_0_2","x":"13","y":"43"},{"name":"hblooza_chicken_32_b_2_3","flipH":"1","source":"hblooza_chicken_32_b_0_3","x":"13","y":"43"},{"name":"hblooza_chicken_64_sd_2_0","flipH":"1","source":"hblooza_chicken_64_sd_0_0","x":"33","y":"16"},{"name":"hblooza_chicken_64_a_2_0","flipH":"1","source":"hblooza_chicken_64_a_0_0","x":"34","y":"134"},{"name":"hblooza_chicken_64_b_2_0","flipH":"1","source":"hblooza_chicken_64_b_0_0","x":"29","y":"84"},{"name":"hblooza_chicken_64_b_2_1","flipH":"1","source":"hblooza_chicken_64_b_0_1","x":"24","y":"84"},{"name":"hblooza_chicken_64_b_2_2","flipH":"1","source":"hblooza_chicken_64_b_0_2","x":"24","y":"84"},{"name":"hblooza_chicken_64_b_2_3","flipH":"1","source":"hblooza_chicken_64_b_0_3","x":"25","y":"84"}]}},"index":{"object":{"type":"hblooza_chicken","visualization":"furniture_animated","logic":"furniture_multistate"}},"logic":{"objectData":{"type":"hblooza_chicken","model":{"dimensions":{"x":"1","y":"1","z":"1"},"directions":{"direction":[{"id":"0"},{"id":"90"}]}},"particlesystems":{"particlesystem":[{"size":"64"},{"size":"32"}]}}},"manifest":{"manifest":{"library":{"name":"hblooza_chicken","version":"0.1","assets":{"asset":[{"name":"index","mimeType":"text/xml"},{"name":"hblooza_chicken_visualization","mimeType":"text/xml"},{"name":"hblooza_chicken_assets","mimeType":"text/xml"},{"name":"hblooza_chicken_logic","mimeType":"text/xml"},{"name":"hblooza_chicken_32_sd_0_0","mimeType":"image/png"},{"name":"hblooza_chicken_32_a_0_0","mimeType":"image/png"},{"name":"hblooza_chicken_32_b_0_0","mimeType":"image/png"},{"name":"hblooza_chicken_32_b_0_1","mimeType":"image/png"},{"name":"hblooza_chicken_32_b_0_2","mimeType":"image/png"},{"name":"hblooza_chicken_32_b_0_3","mimeType":"image/png"},{"name":"hblooza_chicken_64_sd_0_0","mimeType":"image/png"},{"name":"hblooza_chicken_64_a_0_0","mimeType":"image/png"},{"name":"hblooza_chicken_64_b_0_0","mimeType":"image/png"},{"name":"hblooza_chicken_64_b_0_1","mimeType":"image/png"},{"name":"hblooza_chicken_64_b_0_2","mimeType":"image/png"},{"name":"hblooza_chicken_64_b_0_3","mimeType":"image/png"},{"name":"hblooza_chicken_icon_a","mimeType":"image/png"}]}}}},"visualization":{"visualizationData":{"type":"hblooza_chicken","graphics":{"visualization":[{"size":"1","layerCount":"1","angle":"360"},{"size":"32","layerCount":"2","angle":"45","layers":{"layer":{"id":"0"}},"directions":{"direction":[{"id":"0"},{"id":"2"}]},"colors":null,"animations":{"animation":[{"id":"0","animationLayer":[{"id":"0"},{"id":"1","frameRepeat":"4","loopCount":"0","frameSequence":{"frame":[{"id":"0"},{"id":"1"},{"id":"2"},{"id":"3"}]}}]},{"id":"1","animationLayer":[{"id":"0"},{"id":"1","frameSequence":{"frame":{"id":"0"}}}]}]},"postures":null,"gestures":null},{"size":"64","layerCount":"2","angle":"45","layers":{"layer":{"id":"0"}},"directions":{"direction":[{"id":"0"},{"id":"2"}]},"colors":null,"animations":{"animation":[{"id":"0","animationLayer":[{"id":"0"},{"id":"1","loopCount":"0","frameRepeat":"4","frameSequence":{"frame":[{"id":"0"},{"id":"1"},{"id":"2"},{"id":"3"}]}}]},{"id":"1","animationLayer":[{"id":"0"},{"id":"1","frameSequence":{"frame":{"id":"0"}}}]}]},"postures":null,"gestures":null}]}}},"sprites":{"hblooza_chicken_32_a_0_0":{"left":"0","top":"176","width":"35","height":"75"},"hblooza_chicken_32_b_0_0":{"left":"34","top":"0","width":"25","height":"29"},"hblooza_chicken_32_b_0_1":{"left":"59","top":"0","width":"22","height":"29"},"hblooza_chicken_32_b_0_2":{"left":"81","top":"0","width":"23","height":"29"},"hblooza_chicken_32_b_0_3":{"left":"0","top":"29","width":"21","height":"29"},"hblooza_chicken_32_sd_0_0":{"left":"0","top":"0","width":"34","height":"17"},"hblooza_chicken_64_a_0_0":{"left":"35","top":"176","width":"67","height":"150"},"hblooza_chicken_64_b_0_0":{"left":"0","top":"62","width":"48","height":"57"},"hblooza_chicken_64_b_0_1":{"left":"48","top":"62","width":"42","height":"57"},"hblooza_chicken_64_b_0_2":{"left":"0","top":"119","width":"44","height":"57"},"hblooza_chicken_64_b_0_3":{"left":"44","top":"119","width":"41","height":"57"},"hblooza_chicken_64_sd_0_0":{"left":"45","top":"29","width":"66","height":"33"},"hblooza_chicken_icon_a":{"left":"21","top":"29","width":"24","height":"30"}}}