{"manifest":{"manifest":{"library":{"name":"shirt_U_flowytop","version":"0.1","assets":{"asset":[{"name":"h_lay_ch_3470_2_0","mimeType":"image/png","param":{"key":"offset","value":"1,24"}},{"name":"h_lay_ch_3471_2_0","mimeType":"image/png","param":{"key":"offset","value":"-15,18"}},{"name":"h_std_ch_3470_7_0","mimeType":"image/png","param":{"key":"offset","value":"-17,46"}},{"name":"h_std_ch_3470_3_0","mimeType":"image/png","param":{"key":"offset","value":"-17,50"}},{"name":"h_std_ch_3470_2_0","mimeType":"image/png","param":{"key":"offset","value":"-19,52"}},{"name":"h_std_ch_3470_1_0","mimeType":"image/png","param":{"key":"offset","value":"-19,46"}},{"name":"h_std_ch_3470_0_0","mimeType":"image/png","param":{"key":"offset","value":"-14,48"}},{"name":"h_std_ch_3471_7_0","mimeType":"image/png","param":{"key":"offset","value":"-18,25"}},{"name":"h_std_ch_3471_3_0","mimeType":"image/png","param":{"key":"offset","value":"-18,29"}},{"name":"h_std_ch_3471_2_0","mimeType":"image/png","param":{"key":"offset","value":"-20,30"}},{"name":"h_std_ch_3471_1_0","mimeType":"image/png","param":{"key":"offset","value":"-20,28"}},{"name":"h_std_ch_3471_0_0","mimeType":"image/png","param":{"key":"offset","value":"-15,27"}},{"name":"h_wlk_rs_3470_2_0","mimeType":"image/png","param":{"key":"offset","value":"-24,46"}},{"name":"h_wlk_rs_3470_2_1","mimeType":"image/png","param":{"key":"offset","value":"-26,43"}},{"name":"h_wlk_rs_3470_2_3","mimeType":"image/png","param":{"key":"offset","value":"-28,39"}},{"name":"h_wlk_rs_3470_0_2","mimeType":"image/png","param":{"key":"offset","value":"-39,44"}},{"name":"h_wlk_rs_3470_0_0","mimeType":"image/png","param":{"key":"offset","value":"-40,43"}},{"name":"h_wlk_rs_3470_0_1","mimeType":"image/png","param":{"key":"offset","value":"-23,43"}},{"name":"h_wlk_rs_3470_0_3","mimeType":"image/png","param":{"key":"offset","value":"-24,43"}},{"name":"h_wlk_rs_3470_1_1","mimeType":"image/png","param":{"key":"offset","value":"-25,42"}},{"name":"h_wlk_ls_3470_3_0","mimeType":"image/png","param":{"key":"offset","value":"-42,49"}},{"name":"h_wlk_ls_3470_3_1","mimeType":"image/png","param":{"key":"offset","value":"-42,48"}},{"name":"h_wlk_ls_3470_3_2","mimeType":"image/png","param":{"key":"offset","value":"-42,49"}},{"name":"h_wlk_ls_3470_3_3","mimeType":"image/png","param":{"key":"offset","value":"-42,48"}},{"name":"h_wlk_rs_3470_3_1","mimeType":"image/png","param":{"key":"offset","value":"-23,40"}},{"name":"h_wlk_rs_3470_3_3","mimeType":"image/png","param":{"key":"offset","value":"-24,40"}},{"name":"h_drk_rs_3470_2_0","mimeType":"image/png","param":{"key":"offset","value":"-27,43"}},{"name":"h_drk_rs_3470_0_0","mimeType":"image/png","param":{"key":"offset","value":"-40,43"}},{"name":"h_wav_ls_3470_6_0","mimeType":"image/png","param":{"key":"offset","value":"-27,44"}},{"name":"h_wav_ls_3470_6_1","mimeType":"image/png","param":{"key":"offset","value":"-27,44"}}]}}}},"sprites":{"shirt_U_flowytop_h_drk_rs_3470_0_0":{"left":"0","top":"0","width":"2","height":"1"},"shirt_U_flowytop_h_drk_rs_3470_2_0":{"left":"5","top":"0","width":"4","height":"2"},"shirt_U_flowytop_h_lay_ch_3470_2_0":{"left":"0","top":"74","width":"41","height":"33"},"shirt_U_flowytop_h_lay_ch_3471_2_0":{"left":"0","top":"42","width":"24","height":"26"},"shirt_U_flowytop_h_std_ch_3470_0_0":{"left":"0","top":"143","width":"33","height":"37"},"shirt_U_flowytop_h_std_ch_3470_1_0":{"left":"24","top":"42","width":"27","height":"32"},"shirt_U_flowytop_h_std_ch_3470_2_0":{"left":"33","top":"143","width":"30","height":"38"},"shirt_U_flowytop_h_std_ch_3470_3_0":{"left":"0","top":"107","width":"32","height":"36"},"shirt_U_flowytop_h_std_ch_3470_7_0":{"left":"32","top":"107","width":"32","height":"36"},"shirt_U_flowytop_h_std_ch_3471_0_0":{"left":"0","top":"27","width":"31","height":"15"},"shirt_U_flowytop_h_std_ch_3471_1_0":{"left":"28","top":"0","width":"25","height":"13"},"shirt_U_flowytop_h_std_ch_3471_2_0":{"left":"31","top":"27","width":"28","height":"15"},"shirt_U_flowytop_h_std_ch_3471_3_0":{"left":"0","top":"13","width":"30","height":"14"},"shirt_U_flowytop_h_std_ch_3471_7_0":{"left":"30","top":"13","width":"30","height":"14"},"shirt_U_flowytop_h_wav_ls_3470_6_1":{"left":"18","top":"0","width":"2","height":"4"},"shirt_U_flowytop_h_wlk_ls_3470_3_1":{"left":"24","top":"0","width":"2","height":"10"},"shirt_U_flowytop_h_wlk_ls_3470_3_2":{"left":"16","top":"0","width":"2","height":"3"},"shirt_U_flowytop_h_wlk_ls_3470_3_3":{"left":"26","top":"0","width":"2","height":"10"},"shirt_U_flowytop_h_wlk_rs_3470_0_0":{"left":"2","top":"0","width":"2","height":"1"},"shirt_U_flowytop_h_wlk_rs_3470_0_1":{"left":"0","top":"181","width":"19","height":"101"},"shirt_U_flowytop_h_wlk_rs_3470_0_2":{"left":"9","top":"0","width":"1","height":"2"},"shirt_U_flowytop_h_wlk_rs_3470_0_3":{"left":"19","top":"181","width":"18","height":"101"},"shirt_U_flowytop_h_wlk_rs_3470_1_1":{"left":"10","top":"0","width":"3","height":"2"},"shirt_U_flowytop_h_wlk_rs_3470_2_0":{"left":"20","top":"0","width":"4","height":"8"},"shirt_U_flowytop_h_wlk_rs_3470_2_1":{"left":"4","top":"0","width":"1","height":"1"},"shirt_U_flowytop_h_wlk_rs_3470_3_1":{"left":"13","top":"0","width":"2","height":"2"},"shirt_U_flowytop_h_wlk_rs_3470_3_3":{"left":"15","top":"0","width":"1","height":"2"},"shirt_U_flowytop_h_wlk_rs_3470_2_3":{"link":"shirt_U_flowytop_h_wlk_rs_3470_3_3"},"shirt_U_flowytop_h_wav_ls_3470_6_0":{"link":"shirt_U_flowytop_h_wav_ls_3470_6_1"},"shirt_U_flowytop_h_wlk_ls_3470_3_0":{"link":"shirt_U_flowytop_h_wlk_ls_3470_3_2"}}}